jumi/__init__.py
jumi/metadata.py
jumi-0.0.1.dist-info/METADATA
jumi-0.0.1.dist-info/WHEEL
jumi-0.0.1.dist-info/entry_points.txt
jumi-0.0.1.dist-info/RECORD
