Metadata-Version: 2.3
Name: jumi
Version: 0.0.1
Summary: A helper script for the jumi project
Project-URL: Documentation, https://gitlab.jsc.fz-juelich.de/exacb/jumi
Project-URL: Issues, https://gitlab.jsc.fz-juelich.de/exacb/jumi
Project-URL: Source, https://gitlab.jsc.fz-juelich.de/exacb/jumi
Author-email: Jayesh Badwaik <j.badwaik@fz-juelich.de>
License-Expression: Apache-2.0
Requires-Dist: semver
